README.md
setup.py
replemail/__init__.py
replemail.egg-info/PKG-INFO
replemail.egg-info/SOURCES.txt
replemail.egg-info/dependency_links.txt
replemail.egg-info/not-zip-safe
replemail.egg-info/requires.txt
replemail.egg-info/top_level.txt