Metadata-Version: 1.0
Name: replemail
Version: 1.0.0
Summary: API for https://repl.email
Home-page: https://github.com/AgeOfMarcus/replemail
Author: AgeOfMarcus
Author-email: marcus@marcusweinberger.com
License: UNKNOWN
Platform: UNKNOWN
